src/cpu16.v
`timescale 1ns/1ps

module x86_cpu(
    input clk,
    input reset,
    output reg [15:0] mem_addr,
    output reg [15:0] mem_wdata,
    output reg mem_we,
    input [15:0] mem_rdata
);

reg [15:0] AX,BX,CX,DX,SP,BP,SI,DI;
reg [15:0] IP,IR;
reg ZF,CF,SF,OF;
reg [2:0] state;

reg [15:0] src_data;
reg [15:0] result;

localparam FETCH  = 3'd0;
localparam DECODE = 3'd1;
localparam EXEC   = 3'd2;
localparam MEM_RD = 3'd3;
localparam MEM_WR = 3'd4;

localparam NOP  = 4'h0;
localparam MOV  = 4'h1;
localparam ADD  = 4'h2;
localparam SUB  = 4'h3;
localparam AND_ = 4'h4;
localparam OR_  = 4'h5;
localparam XOR_ = 4'h6;
localparam CMP  = 4'h7;
localparam JMP  = 4'h8;
localparam JZ   = 4'h9;
localparam JNZ  = 4'hA;
localparam PUSH = 4'hB;
localparam POP  = 4'hC;
localparam HLT  = 4'hF;

always @(*) begin
    case(IR[2:0])
        3'd0: src_data = AX;
        3'd1: src_data = BX;
        3'd2: src_data = CX;
        3'd3: src_data = DX;
        3'd4: src_data = SP;
        3'd5: src_data = BP;
        3'd6: src_data = SI;
        3'd7: src_data = DI;
        default: src_data = 16'h0000;
    endcase
end

always @(posedge clk) begin
    if(reset) begin
        AX <= 0;
        BX <= 0;
        CX <= 0;
        DX <= 0;
        SP <= 16'hFFFE;
        BP <= 0;
        SI <= 0;
        DI <= 0;
        IP <= 0;
        IR <= 0;
        ZF <= 0;
        CF <= 0;
        SF <= 0;
        OF <= 0;
        mem_addr <= 0;
        mem_wdata <= 0;
        mem_we <= 0;
        state <= FETCH;
    end
    else begin
        case(state)

            FETCH: begin
                mem_we <= 0;
                mem_addr <= IP;
                state <= DECODE;
            end

            DECODE: begin
                IR <= mem_rdata;
                state <= EXEC;
            end

            EXEC: begin
                case(IR[15:12])

                    NOP: begin
                        IP <= IP + 1;
                        state <= FETCH;
                    end

                    MOV: begin
                        case(IR[11:9])
                            3'd0: AX <= src_data;
                            3'd1: BX <= src_data;
                            3'd2: CX <= src_data;
                            3'd3: DX <= src_data;
                            3'd4: SP <= src_data;
                            3'd5: BP <= src_data;
                            3'd6: SI <= src_data;
                            3'd7: DI <= src_data;
                        endcase
                        IP <= IP + 1;
                        state <= FETCH;
                    end

                    ADD: begin
                        case(IR[11:9])
                            3'd0: begin
                                result = AX + src_data;
                                AX <= result;
                            end
                            3'd1: begin
                                result = BX + src_data;
                                BX <= result;
                            end
                            3'd2: begin
                                result = CX + src_data;
                                CX <= result;
                            end
                            3'd3: begin
                                result = DX + src_data;
                                DX <= result;
                            end
                            default: result = 0;
                        endcase
                        ZF <= (result == 0);
                        SF <= result[15];
                        IP <= IP + 1;
                        state <= FETCH;
                    end

                    SUB: begin
                        case(IR[11:9])
                            3'd0: begin
                                result = AX - src_data;
                                AX <= result;
                            end
                            3'd1: begin
                                result = BX - src_data;
                                BX <= result;
                            end
                            3'd2: begin
                                result = CX - src_data;
                                CX <= result;
                            end
                            3'd3: begin
                                result = DX - src_data;
                                DX <= result;
                            end
                            default: result = 0;
                        endcase
                        ZF <= (result == 0);
                        SF <= result[15];
                        IP <= IP + 1;
                        state <= FETCH;
                    end

                    AND_: begin
                        case(IR[11:9])
                            3'd0: AX <= AX & src_data;
                            3'd1: BX <= BX & src_data;
                            3'd2: CX <= CX & src_data;
                            3'd3: DX <= DX & src_data;
                        endcase
                        IP <= IP + 1;
                        state <= FETCH;
                    end

                    OR_: begin
                        case(IR[11:9])
                            3'd0: AX <= AX | src_data;
                            3'd1: BX <= BX | src_data;
                            3'd2: CX <= CX | src_data;
                            3'd3: DX <= DX | src_data;
                        endcase
                        IP <= IP + 1;
                        state <= FETCH;
                    end

                    XOR_: begin
                        case(IR[11:9])
                            3'd0: AX <= AX ^ src_data;
                            3'd1: BX <= BX ^ src_data;
                            3'd2: CX <= CX ^ src_data;
                            3'd3: DX <= DX ^ src_data;
                        endcase
                        IP <= IP + 1;
                        state <= FETCH;
                    end

                    CMP: begin
                        case(IR[11:9])
                            3'd0: result = AX - src_data;
                            3'd1: result = BX - src_data;
                            3'd2: result = CX - src_data;
                            3'd3: result = DX - src_data;
                            default: result = 0;
                        endcase
                        ZF <= (result == 0);
                        SF <= result[15];
                        IP <= IP + 1;
                        state <= FETCH;
                    end

                    JMP: begin
                        IP <= {4'b0000,IR[11:0]};
                        state <= FETCH;
                    end

                    JZ: begin
                        if(ZF)
                            IP <= {4'b0000,IR[11:0]};
                        else
                            IP <= IP + 1;
                        state <= FETCH;
                    end

                    JNZ: begin
                        if(!ZF)
                            IP <= {4'b0000,IR[11:0]};
                        else
                            IP <= IP + 1;
                        state <= FETCH;
                    end

                    PUSH: begin
                        SP <= SP - 1;
                        mem_addr <= SP - 1;
                        mem_wdata <= src_data;
                        mem_we <= 1;
                        IP <= IP + 1;
                        state <= MEM_WR;
                    end

                    POP: begin
                        mem_addr <= SP;
                        mem_we <= 0;
                        state <= MEM_RD;
                    end

                    HLT: begin
                        state <= EXEC;
                    end

                    default: begin
                        IP <= IP + 1;
                        state <= FETCH;
                    end

                endcase
            end

            MEM_WR: begin
                mem_we <= 0;
                state <= FETCH;
            end

            MEM_RD: begin
                case(IR[11:9])
                    3'd0: AX <= mem_rdata;
                    3'd1: BX <= mem_rdata;
                    3'd2: CX <= mem_rdata;
                    3'd3: DX <= mem_rdata;
                    3'd4: SP <= mem_rdata;
                    3'd5: BP <= mem_rdata;
                    3'd6: SI <= mem_rdata;
                    3'd7: DI <= mem_rdata;
                endcase
                SP <= SP + 1;
                IP <= IP + 1;
                state <= FETCH;
            end

            default: state <= FETCH;

        endcase
    end
end

endmodule

tb/tb_cpu16.v
`timescale 1ns/1ps

module tb_cpu16;

reg clk;
reg reset;

wire [15:0] mem_addr;
wire [15:0] mem_wdata;
wire        mem_we;
reg  [15:0] mem_rdata;

reg [15:0] memory [0:65535];

integer i;

x86_cpu uut (
    .clk       (clk),
    .reset     (reset),
    .mem_addr  (mem_addr),
    .mem_wdata (mem_wdata),
    .mem_we    (mem_we),
    .mem_rdata (mem_rdata)
);

/* Clock */
always #5 clk = ~clk;

/* Combinational read memory */
always @(*) begin
    mem_rdata = memory[mem_addr];
end

/* Synchronous write memory */
always @(posedge clk) begin
    if (mem_we)
        memory[mem_addr] <= mem_wdata;
end

function [15:0] INST;
    input [3:0] opcode;
    input [2:0] dst;
    input [2:0] src;
    begin
        INST = {opcode, dst, 3'b000, src, 3'b000};
    end
endfunction

function [15:0] JMP_INST;
    input [3:0] opcode;
    input [11:0] address;
    begin
        JMP_INST = {opcode, address};
    end
endfunction

initial begin

    /* Initialize testbench signals */
    clk       = 1'b0;
    reset     = 1'b1;
    mem_rdata = 16'h0000;

    /* Initialize whole memory */
    for (i = 0; i < 65536; i = i + 1)
        memory[i] = 16'h0000;

    /* Waveform */
    $dumpfile("wave/cpu16.vcd");
    $dumpvars(0, tb_cpu16);

    /*
     * Program
     */

    /* 0: NOP */
    memory[0] = 16'h0000;

    /* 1: MOV AX,AX */
    memory[1] = INST(4'h1, 3'd0, 3'd0);

    /* 2: MOV BX,BX */
    memory[2] = INST(4'h1, 3'd1, 3'd1);

    /* 3: MOV CX,CX */
    memory[3] = INST(4'h1, 3'd2, 3'd2);

    /* 4: MOV DX,DX */
    memory[4] = INST(4'h1, 3'd3, 3'd3);

    /* 5: ADD AX,BX */
    memory[5] = INST(4'h2, 3'd0, 3'd1);

    /* 6: ADD BX,CX */
    memory[6] = INST(4'h2, 3'd1, 3'd2);

    /* 7: ADD CX,DX */
    memory[7] = INST(4'h2, 3'd2, 3'd3);

    /* 8: ADD DX,AX */
    memory[8] = INST(4'h2, 3'd3, 3'd0);

    /* 9: SUB AX,BX */
    memory[9] = INST(4'h3, 3'd0, 3'd1);

    /* 10: SUB BX,CX */
    memory[10] = INST(4'h3, 3'd1, 3'd2);

    /* 11: SUB CX,DX */
    memory[11] = INST(4'h3, 3'd2, 3'd3);

    /* 12: SUB DX,AX */
    memory[12] = INST(4'h3, 3'd3, 3'd0);

    /* 13: AND AX,BX */
    memory[13] = INST(4'h4, 3'd0, 3'd1);

    /* 14: OR BX,CX */
    memory[14] = INST(4'h5, 3'd1, 3'd2);

    /* 15: XOR CX,DX */
    memory[15] = INST(4'h6, 3'd2, 3'd3);

    /* 16: CMP AX,BX */
    memory[16] = INST(4'h7, 3'd0, 3'd1);

    /* 17: PUSH AX */
    memory[17] = INST(4'hB, 3'd0, 3'd0);

    /* 18: PUSH BX */
    memory[18] = INST(4'hB, 3'd1, 3'd1);

    /* 19: POP BX */
    memory[19] = INST(4'hC, 3'd1, 3'd1);

    /* 20: POP AX */
    memory[20] = INST(4'hC, 3'd0, 3'd0);

    /* 21: JMP 23 */
    memory[21] = JMP_INST(4'h8, 12'd23);

    /* 22: NOP -- should be skipped */
    memory[22] = 16'h0000;

    /* 23: NOP */
    memory[23] = 16'h0000;

    /* 24: HLT */
    memory[24] = 16'hF000;

    /*
     * Keep testbench reset active for 2 clock cycles.
     * This removes initial X values before normal operation.
     */
    #20;
    @(negedge clk);
    reset = 1'b0;

    /* Let CPU run */
    #300;

    $display("======================================");
    $display("SIMULATION COMPLETED");
    $display("AX = %h", uut.AX);
    $display("BX = %h", uut.BX);
    $display("CX = %h", uut.CX);
    $display("DX = %h", uut.DX);
    $display("SP = %h", uut.SP);
    $display("IP = %h", uut.IP);
    $display("ZF = %b", uut.ZF);
    $display("SF = %b", uut.SF);
    $display("STATE = %d", uut.state);
    $display("======================================");

    $finish;

end

initial begin

    $monitor(
        "TIME=%0t RESET=%b STATE=%0d IP=%04h IR=%04h AX=%04h BX=%04h CX=%04h DX=%04h SP=%04h BP=%04h SI=%04h DI=%04h ZF=%b SF=%b MEM_WE=%b ADDR=%04h WDATA=%04h",
        $time,
        reset,
        uut.state,
        uut.IP,
        uut.IR,
        uut.AX,
        uut.BX,
        uut.CX,
        uut.DX,
        uut.SP,
        uut.BP,
        uut.SI,
        uut.DI,
        uut.ZF,
        uut.SF,
        mem_we,
        mem_addr,
        mem_wdata
    );

end

endmodule

wave/cpu16.vcd
$date
	Sat Sep 12 12:55:16 2026
$end
$version
	Icarus Verilog
$end
$timescale
	1ps
$end
$scope module tb_cpu16 $end
$var wire 1 ! mem_we $end
$var wire 16 " mem_wdata [15:0] $end
$var wire 16 # mem_addr [15:0] $end
$var reg 1 $ clk $end
$var reg 16 % mem_rdata [15:0] $end
$var reg 1 & reset $end
$var integer 32 ' i [31:0] $end
$scope function INST $end
$var reg 3 ( dst [2:0] $end
$var reg 4 ) opcode [3:0] $end
$var reg 3 * src [2:0] $end
$upscope $end
$scope function JMP_INST $end
$var reg 12 + address [11:0] $end
$var reg 4 , opcode [3:0] $end
$upscope $end
$scope module uut $end
$var wire 1 $ clk $end
$var wire 16 - mem_rdata [15:0] $end
$var wire 1 & reset $end
$var parameter 4 . ADD $end
$var parameter 4 / AND_ $end
$var parameter 4 0 CMP $end
$var parameter 3 1 DECODE $end
$var parameter 3 2 EXEC $end
$var parameter 3 3 FETCH $end
$var parameter 4 4 HLT $end
$var parameter 4 5 JMP $end
$var parameter 4 6 JNZ $end
$var parameter 4 7 JZ $end
$var parameter 3 8 MEM_RD $end
$var parameter 3 9 MEM_WR $end
$var parameter 4 : MOV $end
$var parameter 4 ; NOP $end
$var parameter 4 < OR_ $end
$var parameter 4 = POP $end
$var parameter 4 > PUSH $end
$var parameter 4 ? SUB $end
$var parameter 4 @ XOR_ $end
$var reg 16 A AX [15:0] $end
$var reg 16 B BP [15:0] $end
$var reg 16 C BX [15:0] $end
$var reg 1 D CF $end
$var reg 16 E CX [15:0] $end
$var reg 16 F DI [15:0] $end
$var reg 16 G DX [15:0] $end
$var reg 16 H IP [15:0] $end
$var reg 16 I IR [15:0] $end
$var reg 1 J OF $end
$var reg 1 K SF $end
$var reg 16 L SI [15:0] $end
$var reg 16 M SP [15:0] $end
$var reg 1 N ZF $end
$var reg 16 O mem_addr [15:0] $end
$var reg 16 P mem_wdata [15:0] $end
$var reg 1 ! mem_we $end
$var reg 16 Q result [15:0] $end
$var reg 16 R src_data [15:0] $end
$var reg 3 S state [2:0] $end
$upscope $end
$upscope $end
$enddefinitions $end
$comment Show the parameter values. $end
$dumpall
b110 @
b11 ?
b1011 >
b1100 =
b101 <
b0 ;
b1 :
b100 9
b11 8
b1001 7
b1010 6
b1000 5
b1111 4
b0 3
b10 2
b1 1
b111 0
b100 /
b10 .
$end
#0
$dumpvars
bx S
bx R
bx Q
bx P
bx O
xN
bx M
bx L
xK
xJ
bx I
bx H
bx G
bx F
bx E
xD
bx C
bx B
bx A
bx -
b1000 ,
b10111 +
b0 *
b1100 )
b0 (
b10000000000000000 '
1&
bx %
0$
bx #
bx "
x!
$end
#5000
b0 %
b0 -
b0 R
b0 S
0!
b0 "
b0 P
b0 #
b0 O
0J
0K
0D
0N
b0 I
b0 H
b0 F
b0 L
b0 B
b1111111111111110 M
b0 G
b0 E
b0 C
b0 A
1$
#10000
0$
#15000
1$
#20000
0&
0$
#25000
b1 S
1$
#30000
0$
#35000
b10 S
1$
#40000
0$
#45000
b0 S
b1 H
1$
#50000
0$
#55000
b1000000000000 %
b1000000000000 -
b1 S
b1 #
b1 O
1$
#60000
0$
#65000
b10 S
b1000000000000 I
1$
#70000
0$
#75000
b0 S
b10 H
1$
#80000
0$
#85000
b1001000001000 %
b1001000001000 -
b1 S
b10 #
b10 O
1$
#90000
0$
#95000
b10 S
b1001000001000 I
1$
#100000
0$
#105000
b0 S
b11 H
1$
#110000
0$
#115000
b1010000010000 %
b1010000010000 -
b1 S
b11 #
b11 O
1$
#120000
0$
#125000
b10 S
b1010000010000 I
1$
#130000
0$
#135000
b0 S
b100 H
1$
#140000
0$
#145000
b1011000011000 %
b1011000011000 -
b1 S
b100 #
b100 O
1$
#150000
0$
#155000
b10 S
b1011000011000 I
1$
#160000
0$
#165000
b0 S
b101 H
1$
#170000
0$
#175000
b10000000001000 %
b10000000001000 -
b1 S
b101 #
b101 O
1$
#180000
0$
#185000
b10 S
b10000000001000 I
1$
#190000
0$
#195000
b0 S
b110 H
1N
b0 Q
1$
#200000
0$
#205000
b10001000010000 %
b10001000010000 -
b1 S
b110 #
b110 O
1$
#210000
0$
#215000
b10 S
b10001000010000 I
1$
#220000
0$
#225000
b0 S
b111 H
1$
#230000
0$
#235000
b10010000011000 %
b10010000011000 -
b1 S
b111 #
b111 O
1$
#240000
0$
#245000
b10 S
b10010000011000 I
1$
#250000
0$
#255000
b0 S
b1000 H
1$
#260000
0$
#265000
b10011000000000 %
b10011000000000 -
b1 S
b1000 #
b1000 O
1$
#270000
0$
#275000
b10 S
b10011000000000 I
1$
#280000
0$
#285000
b0 S
b1001 H
1$
#290000
0$
#295000
b11000000001000 %
b11000000001000 -
b1 S
b1001 #
b1001 O
1$
#300000
0$
#305000
b10 S
b11000000001000 I
1$
#310000
0$
#315000
b0 S
b1010 H
1$
